[{"id":1,"version":"1.0-1.23","date":1285869600000,"name":{"de":"Final Fantasy XIV 1.0","en":"Final Fantasy XIV 1.0","fr":"Final Fantasy XIV 1.0","jp":"Final Fantasy XIV 1.0"}},{"id":2,"version":"2.0","date":1376607600000,"name":{"de":"A Realm Reborn","en":"A Realm Reborn","fr":"A Realm Reborn","jp":"新生エオルゼア 2.0"},"image":"/patches/2.0.png","counts":{"achievements":{"change":811,"percent":100},"minions":{"change":42,"percent":100},"mounts":{"change":7,"percent":100},"titles":{"change":111,"percent":100}}},{"id":3,"version":"2.05","date":1382032800000,"name":{"de":"Halloween 2013","en":"Halloween 2013","fr":"Halloween 2013","jp":"Halloween 2013"},"counts":{"achievements":{"change":1,"percent":0.1}}},{"id":4,"version":"2.1","date":1387245600000,"name":{"de":"A Realm Awoken","en":"A Realm Awoken","fr":"A Realm Awoken","jp":"A Realm Awoken"},"image":"/patches/2.1.png","counts":{"achievements":{"change":62,"percent":7.1},"minions":{"change":21,"percent":33.3},"mounts":{"change":5,"percent":41.7},"titles":{"change":24,"percent":17.8}}},{"id":6,"version":"2.15","date":1390255200000,"name":{"de":"Patch 2.15","en":"Patch 2.15","fr":"Patch 2.15","jp":"Patch 2.15"}},{"id":7,"version":"2.16","date":1392919200000,"name":{"de":"Patch 2.16","en":"Patch 2.16","fr":"Patch 2.16","jp":"Patch 2.16"}},{"id":8,"version":"2.2","date":1395831600000,"name":{"de":"Through The Maelstrom","en":"Through The Maelstrom","fr":"Through The Maelstrom","jp":"Through The Maelstrom"},"image":"/patches/2.2.png","counts":{"achievements":{"change":39,"percent":4.3},"minions":{"change":11,"percent":14.9},"mounts":{"change":9,"percent":42.9},"titles":{"change":7,"percent":4.9}}},{"id":9,"version":"2.25","date":1398326400000,"name":{"de":"Patch 2.25","en":"Patch 2.25","fr":"Patch 2.25","jp":"Patch 2.25"},"counts":{"achievements":{"change":1,"percent":0.1}}},{"id":10,"version":"2.28","date":1401948000000,"name":{"de":"Patch 2.28","en":"Patch 2.28","fr":"Patch 2.28","jp":"Patch 2.28"},"counts":{"achievements":{"change":3,"percent":0.3},"minions":{"change":1,"percent":1.3}}},{"id":11,"version":"2.3","date":1404774000000,"name":{"de":"Defenders Of Eorzea","en":"Defenders Of Eorzea","fr":"Defenders Of Eorzea","jp":"Defenders Of Eorzea"},"image":"/patches/2.3.png","counts":{"achievements":{"change":87,"percent":8.7},"minions":{"change":18,"percent":19.4},"mounts":{"change":5,"percent":19.2},"titles":{"change":20,"percent":12.3}}},{"id":12,"version":"2.35","date":1408420800000,"name":{"de":"Patch 2.35","en":"Patch 2.35","fr":"Patch 2.35","jp":"Patch 2.35"},"counts":{"achievements":{"change":6,"percent":0.6},"minions":{"change":6,"percent":6.1},"mounts":{"change":1,"percent":3.7},"titles":{"change":2,"percent":1.2}}},{"id":13,"version":"2.38","date":1410804000000,"name":{"de":"Patch 2.38","en":"Patch 2.38","fr":"Patch 2.38","jp":"Patch 2.38"},"counts":{"achievements":{"change":2,"percent":0.2},"minions":{"change":5,"percent":4.8},"mounts":{"change":1,"percent":3.6}}},{"id":14,"version":"2.4","date":1414465200000,"name":{"de":"Dreams Of Ice","en":"Dreams Of Ice","fr":"Dreams Of Ice","jp":"Dreams Of Ice"},"image":"/patches/2.4.png","counts":{"achievements":{"change":25,"percent":2.4},"minions":{"change":9,"percent":8},"mounts":{"change":2,"percent":6.7},"titles":{"change":5,"percent":3}}},{"id":15,"version":"2.45","date":1418097600000,"name":{"de":"Patch 2.45","en":"Patch 2.45","fr":"Patch 2.45","jp":"Patch 2.45"},"counts":{"achievements":{"change":4,"percent":0.4},"minions":{"change":4,"percent":3.4},"mounts":{"change":1,"percent":3.2}}},{"id":16,"version":"2.5","date":1421722800000,"name":{"de":"Before The Fall","en":"Before The Fall","fr":"Before The Fall","jp":"Before The Fall"},"image":"/patches/2.5.png","counts":{"achievements":{"change":20,"percent":1.9},"minions":{"change":5,"percent":4.1},"mounts":{"change":2,"percent":6.1},"titles":{"change":9,"percent":5.1}}},{"id":17,"version":"2.51","date":1424746800000,"name":{"de":"Patch 2.51","en":"Patch 2.51","fr":"Patch 2.51","jp":"Patch 2.51"},"counts":{"achievements":{"change":49,"percent":4.4},"minions":{"change":2,"percent":1.6},"mounts":{"change":2,"percent":5.7},"titles":{"change":18,"percent":9.2}}},{"id":18,"version":"2.55","date":1427760000000,"name":{"de":"Patch 2.55","en":"Patch 2.55","fr":"Patch 2.55","jp":"Patch 2.55"},"counts":{"achievements":{"change":4,"percent":0.4},"titles":{"change":3,"percent":1.5}}},{"id":19,"version":"3.0","date":1434679200000,"name":{"de":"Heavensward","en":"Heavensward","fr":"Heavensward","jp":"蒼天のイシュガルド 3.0"},"image":"/patches/3.0.png","counts":{"achievements":{"change":189,"percent":14.5},"minions":{"change":21,"percent":14.5},"mounts":{"change":7,"percent":16.7},"titles":{"change":44,"percent":18.1}}},{"id":20,"version":"3.01","date":1436259600000,"name":{"de":"Patch 3.01","en":"Patch 3.01","fr":"Patch 3.01","jp":"Patch 3.01"},"counts":{"achievements":{"change":8,"percent":0.6},"minions":{"change":3,"percent":2},"titles":{"change":1,"percent":0.4}}},{"id":21,"version":"3.05","date":1437469200000,"name":{"de":"Patch 3.05","en":"Patch 3.05","fr":"Patch 3.05","jp":"Patch 3.05"},"counts":{"achievements":{"change":14,"percent":1.1},"minions":{"change":1,"percent":0.7},"mounts":{"change":1,"percent":2.3},"titles":{"change":1,"percent":0.4}}},{"id":22,"version":"3.07","date":1440495000000,"name":{"de":"Patch 3.07","en":"Patch 3.07","fr":"Patch 3.07","jp":"Patch 3.07"},"counts":{"achievements":{"change":3,"percent":0.2},"minions":{"change":3,"percent":2},"mounts":{"change":1,"percent":2.3}}},{"id":23,"version":"3.1","date":1447063200000,"name":{"de":"As Goes Light, So Goes Darkness","en":"As Goes Light, So Goes Darkness","fr":"Entre Lumière et Ténèbres","jp":"As Goes Light, So Goes Darkness"},"image":"/patches/3.1.png","counts":{"achievements":{"change":39,"percent":2.9},"minions":{"change":13,"percent":7.9},"mounts":{"change":5,"percent":10.2},"titles":{"change":11,"percent":4.3}}},{"id":24,"version":"3.15","date":1450263600000,"name":{"de":"Patch 3.15","en":"Patch 3.15","fr":"Patch 3.15","jp":"Patch 3.15"},"counts":{"achievements":{"change":17,"percent":1.2},"titles":{"change":2,"percent":0.8}}},{"id":25,"version":"3.2","date":1456221650000,"name":{"de":"The Gears Of Change","en":"The Gears Of Change","fr":"The Gears Of Change","jp":"The Gears Of Change"},"image":"/patches/3.2.png","counts":{"achievements":{"change":65,"percent":4.5},"minions":{"change":13,"percent":7.3},"mounts":{"change":8,"percent":14},"titles":{"change":13,"percent":4.8}}},{"id":26,"version":"3.25","date":1459234800000,"name":{"de":"Patch 3.25","en":"Patch 3.25","fr":"Patch 3.25","jp":"Patch 3.25"},"counts":{"achievements":{"change":15,"percent":1},"minions":{"change":2,"percent":1.1},"mounts":{"change":1,"percent":1.7}}},{"id":27,"version":"3.3","date":1465203600000,"name":{"de":"Revenge Of The Horde","en":"Revenge Of The Horde","fr":"Revenge Of The Horde","jp":"Revenge Of The Horde"},"image":"/patches/3.3.png","counts":{"achievements":{"change":42,"percent":2.8},"minions":{"change":10,"percent":5.3},"mounts":{"change":4,"percent":6.5},"titles":{"change":6,"percent":2.2}}},{"id":28,"version":"3.35","date":1468915200000,"name":{"de":"Patch 3.35","en":"Patch 3.35","fr":"Patch 3.35","jp":"Patch 3.35"},"counts":{"achievements":{"change":66,"percent":4.2},"minions":{"change":17,"percent":8.2},"mounts":{"change":4,"percent":6.1},"titles":{"change":17,"percent":5.8}}},{"id":30,"version":"3.4","date":1474959600000,"name":{"de":"Soul Surrender","en":"Soul Surrender","fr":"Soul Surrender","jp":"Soul Surrender"},"image":"/patches/3.4.png","counts":{"achievements":{"change":37,"percent":2.3},"minions":{"change":10,"percent":4.6},"mounts":{"change":3,"percent":4.3},"titles":{"change":6,"percent":2}}},{"id":31,"version":"3.45","date":1477994400000,"name":{"de":"Patch 3.45","en":"Patch 3.45","fr":"Patch 3.45","jp":"Patch 3.45"},"counts":{"achievements":{"change":22,"percent":1.3},"titles":{"change":4,"percent":1.3}}},{"id":32,"version":"3.5","date":1484643600000,"name":{"de":"The Far Edge Of Fate","en":"The Far Edge Of Fate","fr":"The Far Edge Of Fate","jp":"The Far Edge Of Fate"},"image":"/patches/3.5.png","counts":{"achievements":{"change":55,"percent":3.3},"minions":{"change":10,"percent":4.4},"mounts":{"change":8,"percent":10.4},"titles":{"change":19,"percent":5.9}}},{"id":33,"version":"3.55a","date":1485594000000,"name":{"de":"Patch 3.55a","en":"Patch 3.55a","fr":"Patch 3.55a","jp":"Patch 3.55a"},"counts":{"achievements":{"change":35,"percent":2},"minions":{"change":3,"percent":1.3},"mounts":{"change":2,"percent":2.5},"titles":{"change":6,"percent":1.8}}},{"id":34,"version":"3.55b","date":1489050000000,"name":{"de":"Patch 3.55b","en":"Patch 3.55b","fr":"Patch 3.55b","jp":"Patch 3.55b"},"counts":{"achievements":{"change":8,"percent":0.5},"minions":{"change":2,"percent":0.9}}},{"id":35,"version":"3.56","date":1490688000000,"name":{"de":"Patch 3.56","en":"Patch 3.56","fr":"Patch 3.56","jp":"Patch 3.56"},"counts":{"achievements":{"change":1,"percent":0.1},"mounts":{"change":1,"percent":1.3},"titles":{"change":1,"percent":0.3}}},{"id":36,"version":"4.0","date":1497513600000,"name":{"de":"Stormblood","en":"Stormblood","fr":"Stormblood","jp":"Stormblood"},"image":"/patches/4.0.png","counts":{"achievements":{"change":147,"percent":7.8},"minions":{"change":21,"percent":8.3},"mounts":{"change":13,"percent":14},"titles":{"change":32,"percent":8.8}}},{"id":37,"version":"4.01","date":1499158501000,"name":{"de":"Patch 4.01","en":"Patch 4.01","fr":"Patch 4.01","jp":"Patch 4.01"},"counts":{"achievements":{"change":4,"percent":0.2},"minions":{"change":1,"percent":0.4},"titles":{"change":1,"percent":0.3}}},{"id":38,"version":"4.05","date":1500365361000,"name":{"de":"Patch 4.05","en":"Patch 4.05","fr":"Patch 4.05","jp":"Patch 4.05"},"counts":{"achievements":{"change":13,"percent":0.7},"minions":{"change":3,"percent":1.2},"mounts":{"change":2,"percent":2.1},"titles":{"change":3,"percent":0.8}}},{"id":40,"version":"4.1","date":1507618800000,"name":{"de":"The Legend Returns","en":"The Legend Returns","fr":"The Legend Returns","jp":"The Legend Returns"},"image":"/patches/4.1.png","counts":{"achievements":{"change":34,"percent":1.8},"minions":{"change":12,"percent":4.5},"mounts":{"change":8,"percent":7.8},"titles":{"change":8,"percent":2.1}}},{"id":41,"version":"4.11","date":1508835600000,"name":{"de":"Patch 4.11","en":"Patch 4.11","fr":"Patch 4.11","jp":"Patch 4.11"},"counts":{"achievements":{"change":1,"percent":0.1},"titles":{"change":1,"percent":0.3}}},{"id":42,"version":"4.15","date":1511258400000,"name":{"de":"Patch 4.15","en":"Patch 4.15","fr":"Patch 4.15","jp":"Patch 4.15"},"counts":{"achievements":{"change":11,"percent":0.6},"mounts":{"change":2,"percent":1.9},"titles":{"change":2,"percent":0.5}}},{"id":43,"version":"4.2","date":1517227200000,"name":{"de":"Rise of a New Sun","en":"Rise of a New Sun","fr":"Rise of a New Sun","jp":"Rise of a New Sun"},"image":"/patches/4.2.png","counts":{"achievements":{"change":27,"percent":1.4},"minions":{"change":10,"percent":3.6},"mounts":{"change":10,"percent":8.7},"titles":{"change":4,"percent":1}}},{"id":44,"version":"4.25","date":1520935200000,"name":{"de":"Patch 4.25","en":"Patch 4.25","fr":"Patch 4.25","jp":"Patch 4.25"},"counts":{"achievements":{"change":17,"percent":0.9},"minions":{"change":3,"percent":1.1},"mounts":{"change":1,"percent":0.9}}},{"id":45,"version":"4.30","date":1526972400000,"name":{"de":"Under The Moonlight","en":"Under The Moonlight","fr":"Under The Moonlight","jp":"Under The Moonlight"},"image":"/patches/4.3.png","counts":{"achievements":{"change":32,"percent":1.6},"minions":{"change":8,"percent":2.8},"mounts":{"change":5,"percent":4.1},"titles":{"change":7,"percent":1.8}}}]